LICENSE.TXT
MANIFEST.in
fbtest.py
setup.cfg
setup.py
docs/.buildinfo
docs/changelog.html
docs/genindex.html
docs/index.html
docs/introduction.html
docs/new-test-design.html
docs/objects.inv
docs/py-modindex.html
docs/reference.html
docs/search.html
docs/searchindex.js
docs/usage-guide.html
docs/writting-new-tests.html
fbtest.egg-info/PKG-INFO
fbtest.egg-info/SOURCES.txt
fbtest.egg-info/dependency_links.txt
fbtest.egg-info/entry_points.txt
fbtest.egg-info/not-zip-safe
fbtest.egg-info/requires.txt
fbtest.egg-info/top_level.txt