Metadata-Version: 1.1
Name: fbtest
Version: 1.0.5
Summary: Firebird QA tools.
Home-page: http://www.firebirdsql.org/en/quality-assurance-status/
Author: Pavel Cisar
Author-email: pcisar@users.sourceforge.net
License: IDPL
Keywords: Firebird,QA
Platform: UNKNOWN
Classifier: Development Status :: 5 - Production/Stable
Classifier: License :: OSI Approved :: BSD License
Classifier: Operating System :: OS Independent
Classifier: Programming Language :: Python
Classifier: Topic :: Database
Classifier: Topic :: Software Development
Classifier: Intended Audience :: Developers 
